aiophyn/__init__.py
aiophyn/api.py
aiophyn/const.py
aiophyn/device.py
aiophyn/devices/__init__.py
aiophyn/devices/pp.py
aiophyn/errors.py
aiophyn/home.py
aiophyn/mqtt.py
aiophyn/partners/__init__.py
aiophyn/partners/kohler.py
aiophyn/utils/device_dump.py
aiophyn-2025.10.1.dist-info/METADATA
aiophyn-2025.10.1.dist-info/WHEEL
aiophyn-2025.10.1.dist-info/licenses/LICENSE
aiophyn-2025.10.1.dist-info/RECORD
