Metadata-Version: 2.4
Name: aiophyn
Version: 2025.10.1
Summary: An asynchronous library for Phyn Smart Water devices
License-Expression: MIT
License-File: LICENSE
Author: MizterB
Author-email: 5458030+MizterB@users.noreply.github.com
Requires-Python: >=3.9,<4.0
Classifier: Programming Language :: Python :: 3
Classifier: Programming Language :: Python :: 3.9
Classifier: Programming Language :: Python :: 3.10
Classifier: Programming Language :: Python :: 3.11
Classifier: Programming Language :: Python :: 3.12
Classifier: Programming Language :: Python :: 3.13
Classifier: Programming Language :: Python :: 3.14
Requires-Dist: aiohttp (>=3.8.1,<4.0.0)
Requires-Dist: boto3 (>=1.20.24,<2.0.0)
Requires-Dist: pycognito (>=2022.8.0,<2023.0.0)
Project-URL: Homepage, https://github.com/jordanruthe/aiophyn
Project-URL: Issues, https://github.com/jordanruthe/aiophyn/issues
